.DS_Store
.gitignore
.installed.cfg
.travis.yml
MANIFEST.in
README.rst
buildout.cfg
requirements.txt
setup.py
collective/.DS_Store
collective/__init__.py
collective.logbook.egg-info/PKG-INFO
collective.logbook.egg-info/SOURCES.txt
collective.logbook.egg-info/dependency_links.txt
collective.logbook.egg-info/entry_points.txt
collective.logbook.egg-info/namespace_packages.txt
collective.logbook.egg-info/not-zip-safe
collective.logbook.egg-info/requires.txt
collective.logbook.egg-info/top_level.txt
collective/logbook/.DS_Store
collective/logbook/__init__.py
collective/logbook/config.py
collective/logbook/configure.zcml
collective/logbook/events.py
collective/logbook/interfaces.py
collective/logbook/monkey.py
collective/logbook/profiles.zcml
collective/logbook/setuphandlers.py
collective/logbook/storage.py
collective/logbook/upgradehandlers.py
collective/logbook/utils.py
collective/logbook/browser/__init__.py
collective/logbook/browser/configure.zcml
collective/logbook/browser/controlpanel.py
collective/logbook/browser/errortest.py
collective/logbook/browser/logbook.png
collective/logbook/browser/logbook.pt
collective/logbook/browser/logbook.py
collective/logbook/browser/logbook_atom.pt
collective/logbook/browser/logbook_rss.pt
collective/logbook/browser/mail.pt
collective/logbook/browser/mail.py
collective/logbook/browser/webhook.py
collective/logbook/i18n/collective.logbook-plone-es.mo
collective/logbook/i18n/collective.logbook-plone-es.po
collective/logbook/i18n/collective.logbook-plone.pot
collective/logbook/locales/collective.logbook.pot
collective/logbook/locales/rebuild.sh
collective/logbook/locales/es/LC_MESSAGES/collective.logbook.mo
collective/logbook/locales/es/LC_MESSAGES/collective.logbook.po
collective/logbook/profiles/.DS_Store
collective/logbook/profiles/default/actionicons.xml
collective/logbook/profiles/default/collective.logbook_various.txt
collective/logbook/profiles/default/controlpanel.xml
collective/logbook/profiles/default/metadata.xml
collective/logbook/profiles/default/registry.xml
collective/logbook/profiles/uninstall/collective.logbook_uninstall.txt
collective/logbook/profiles/uninstall/controlpanel.xml
collective/logbook/profiles/uninstall/metadata.xml
collective/logbook/profiles/uninstall/registry.xml
collective/logbook/tests/__init__.py
collective/logbook/tests/base.py
