Metadata-Version: 2.1
Name: collective.logbook
Version: 1.0.0
Summary: Advanced Persistent Error Log
Home-page: https://github.com/collective/collective.logbook
Author: Ramon Bartl
Author-email: rb@ridingbytes.com
License: GPL
Platform: UNKNOWN
Classifier: Framework :: Plone
Classifier: Framework :: Plone :: 4.2
Classifier: Framework :: Plone :: 4.3
Classifier: Framework :: Plone :: 5.0
Classifier: Framework :: Plone :: 5.1
Classifier: Framework :: Plone :: 5.2
Classifier: Programming Language :: Python
Classifier: Topic :: Software Development :: Libraries :: Python Modules
Provides-Extra: test
